pyrankvote/__init__.py
pyrankvote/helpers.py
pyrankvote/models.py
pyrankvote/multiple_seat_ranking_methods.py
pyrankvote/single_seat_ranking_methods.py
pyrankvote/test_helpers.py
pyrankvote-2.0.6.dist-info/LICENSE.txt
pyrankvote-2.0.6.dist-info/METADATA
pyrankvote-2.0.6.dist-info/WHEEL
pyrankvote-2.0.6.dist-info/top_level.txt
pyrankvote-2.0.6.dist-info/RECORD
