Metadata-Version: 2.1
Name: pyrankvote
Version: 2.0.6
Summary: PyRankVote is a python library for different ranked voting methods, like instant-runoff voting, single transferable vote and preferential block voting, created by Jon Tingvold.
Home-page: https://github.com/jontingvold/pyrankvote
Author: Jon Tingvold
Author-email: jon.tingvold@gmail.com
License: MIT
Classifier: Programming Language :: Python :: 3
Classifier: License :: OSI Approved :: MIT License
Classifier: Operating System :: OS Independent
License-File: LICENSE.txt
